adroit/__init__.py
adroit/cli.py
adroit/docker/dockerfile-base.tmpl
adroit/docker/dockerfile-centos.tmpl
adroit/docker/dockerfile-debian.tmpl
adroit/tester.py
adroit-0.3.dist-info/entry_points.txt
adroit-0.3.dist-info/LICENSE
adroit-0.3.dist-info/WHEEL
adroit-0.3.dist-info/METADATA
adroit-0.3.dist-info/RECORD
