Metadata-Version: 2.1
Name: adroit
Version: 0.3
Summary: Ansible Docker Role Testing
Home-page: UNKNOWN
License: MIT
Author: Andreas Lutro
Author-email: anlutro@gmail.com
Requires-Python: >=3.5,<4.0
Classifier: License :: OSI Approved :: MIT License
Classifier: Programming Language :: Python :: 3
Classifier: Programming Language :: Python :: 3.5
Classifier: Programming Language :: Python :: 3.6
Classifier: Programming Language :: Python :: 3.7
